crystal_kernel/__init__.py
crystal_kernel/__main__.py
crystal_kernel/install.py
crystal_kernel/kernel.py
crystal_kernel/resources/__init__.py
crystal_kernel/resources/logo-32x32.png
crystal_kernel/resources/logo-64x64.png
crystal_kernel-0.0.3.dist-info/WHEEL
crystal_kernel-0.0.3.dist-info/METADATA
crystal_kernel-0.0.3.dist-info/RECORD
